declare_cloudinfra_standard_template_library/__init__.py
declare_cloudinfra_standard_template_library/hello_world.py
declare_cloudinfra_standard_template_library-0.0.4.dist-info/LICENSE
declare_cloudinfra_standard_template_library-0.0.4.dist-info/WHEEL
declare_cloudinfra_standard_template_library-0.0.4.dist-info/METADATA
declare_cloudinfra_standard_template_library-0.0.4.dist-info/RECORD
